Metadata-Version: 2.1
Name: cc-report
Version: 0.1.4
Summary: A MODIFIED REPORT
Author: cc.cheng
Author-email: chaicc145@gmail.com
License: MIT
Classifier: Programming Language :: Python :: 3
Classifier: License :: OSI Approved :: MIT License
Classifier: Operating System :: OS Independent
Classifier: Framework :: Pytest
Requires-Python: >=3.6
